kmerfinder-4.0.1.dist-info/METADATA
kmerfinder-4.0.1.dist-info/WHEEL
kmerfinder-4.0.1.dist-info/entry_points.txt
kmerfinder/__init__.py
kmerfinder/__main__.py
kmerfinder-4.0.1.dist-info/RECORD
