Metadata-Version: 2.1
Name: kmerfinder
Version: 4.0.1
Summary: Shim package: KmerFinder is deprecated. Use SpeciesFinder instead.
Author-Email: Center for Genomic Epidemiology <food-cgehelp@dtu.dk>
License: Apache-2.0
Requires-Python: >=3.10
Requires-Dist: speciesfinder>=4.0.1
